zincsearch/__init__.py
zincsearch-1.0.0.dist-info/LICENSE
zincsearch-1.0.0.dist-info/METADATA
zincsearch-1.0.0.dist-info/WHEEL
zincsearch-1.0.0.dist-info/top_level.txt
zincsearch-1.0.0.dist-info/RECORD
