Metadata-Version: 2.1
Name: zincsearch
Version: 1.0.0
Summary: This is a library for [zincsearch](https://zincsearch-docs.zinc.dev/).
Home-page: https://github.com/dabbbby/zincsearch
Author: dabbbby
Author-email: dabbbby@163.com
License: MIT
Platform: any
Classifier: License :: OSI Approved :: MIT License
Classifier: Operating System :: OS Independent
Classifier: Programming Language :: Python :: 3
Requires-Python: >=3.11
License-File: LICENSE
